README.rst
setup.py
org_python.egg-info/PKG-INFO
org_python.egg-info/SOURCES.txt
org_python.egg-info/dependency_links.txt
org_python.egg-info/not-zip-safe
org_python.egg-info/top_level.txt
orgpython/__init__.py
orgpython/document.py
orgpython/inline.py
orgpython/src.py