Metadata-Version: 1.1
Name: org-python
Version: 0.2.8
Summary: convert orgmode to html based on python.
Home-page: https://github.com/honmaple/org-python
Author: honmaple
Author-email: xiyang0807@gmail.com
License: BSD
Platform: any
Classifier: Environment :: Web Environment
Classifier: Intended Audience :: Developers
Classifier: License :: OSI Approved :: BSD License
Classifier: Operating System :: OS Independent
Classifier: Programming Language :: Python
Classifier: Topic :: Internet :: WWW/HTTP :: Dynamic Content
Classifier: Topic :: Software Development :: Libraries :: Python Modules
